[
  {
    "id": 7074,
    "origin": "indomitable",
    "examples": [
      {
        "exam_en": "She showed an <strong class=\"target-word\">indomitable</strong> spirit throughout the crisis.",
        "exam_ko": "그녀는 위기 내내 <strong class=\"target-word\">불굴의</strong> 정신을 보여주었다."
      },
      {
        "exam_en": "My mother had an <strong class=\"target-word\">indomitable</strong> spirit.",
        "exam_ko": "나의 어머니는 <strong class=\"target-word\">불굴의</strong> 정신을 갖고 있었다."
      }
    ]
  },
  {
    "id": 7075,
    "origin": "forfeit",
    "examples": [
      {
        "exam_en": "He had to <strong class=\"target-word\">forfeit</strong> his rights due to the violation.",
        "exam_ko": "그는 위반으로 인해 자신의 권리를 <strong class=\"target-word\">박탈당해야</strong> 했다."
      },
      {
        "exam_en": "The team <strong class=\"target-word\">forfeited</strong> the match after missing the deadline.",
        "exam_ko": "팀은 기한을 놓친 후 경기를 <strong class=\"target-word\">몰수패</strong> 당했다."
      }
    ]
  },
  {
    "id": 7076,
    "origin": "reprieve",
    "examples": [
      {
        "exam_en": "The judge granted him a <strong class=\"target-word\">reprieve</strong> at the last moment.",
        "exam_ko": "판사는 마지막 순간에 그에게 <strong class=\"target-word\">집행 유예</strong>를 허가했다."
      }
    ]
  },
  {
    "id": 7077,
    "origin": "detrimental",
    "examples": [
      {
        "exam_en": "Lack of sleep is <strong class=\"target-word\">detrimental</strong> to one's health.",
        "exam_ko": "수면 부족은 건강에 <strong class=\"target-word\">해롭다</strong>."
      }
    ]
  },
  {
    "id": 7078,
    "origin": "supplant",
    "examples": [
      {
        "exam_en": "Buses are <strong class=\"target-word\">supplanting</strong> streetcars in big cities.",
        "exam_ko": "대도시에서는 버스가 시가 전차를 <strong class=\"target-word\">대신하고</strong> 있다."
      },
      {
        "exam_en": "The new CEO <strong class=\"target-word\">supplanted</strong> the previous leader quickly.",
        "exam_ko": "새 CEO는 전임 리더를 빠르게 <strong class=\"target-word\">대체했다</strong>."
      }
    ]
  },
  {
    "id": 7079,
    "origin": "hindsight",
    "examples": [
      {
        "exam_en": "In <strong class=\"target-word\">hindsight</strong>, we should have left earlier.",
        "exam_ko": "<strong class=\"target-word\">되돌아보면</strong>, 우리는 더 일찍 떠났어야 했다."
      },
      {
        "exam_en": "<strong class=\"target-word\">Hindsight</strong> is 20/20, so don't dwell on past mistakes.",
        "exam_ko": "<strong class=\"target-word\">뒤늦은 깨달음</strong>은 항상 명확하니, 과거의 실수에 집착하지 마라."
      }
    ]
  },
  {
    "id": 7080,
    "origin": "derogatory",
    "examples": [
      {
        "exam_en": "He made a <strong class=\"target-word\">derogatory</strong> remark about her appearance.",
        "exam_ko": "그는 그녀의 외모에 대해 <strong class=\"target-word\">비하하는</strong> 발언을 했다."
      },
      {
        "exam_en": "Such <strong class=\"target-word\">derogatory</strong> comments damage a person's dignity.",
        "exam_ko": "그런 <strong class=\"target-word\">모욕적인</strong> 발언은 사람의 위엄을 손상시킨다."
      }
    ]
  },
  {
    "id": 7081,
    "origin": "slate",
    "examples": [
      {
        "exam_en": "The party has <strong class=\"target-word\">slated</strong> the following members for candidacy.",
        "exam_ko": "당은 하기 당원을 후보자로 <strong class=\"target-word\">지명했다</strong>."
      },
      {
        "exam_en": "The meeting was <strong class=\"target-word\">slated</strong> for May.",
        "exam_ko": "모임은 5월로 <strong class=\"target-word\">예정되었다</strong>."
      }
    ]
  },
  {
    "id": 7082,
    "origin": "atrocious",
    "examples": [
      {
        "exam_en": "The suspect committed an <strong class=\"target-word\">atrocious</strong> crime.",
        "exam_ko": "용의자는 <strong class=\"target-word\">흉악한</strong> 범죄를 저질렀다."
      },
      {
        "exam_en": "Workers endured <strong class=\"target-word\">atrocious</strong> conditions in the factory.",
        "exam_ko": "노동자들은 공장에서 <strong class=\"target-word\">열악한</strong> 환경을 견뎌냈다."
      }
    ]
  },
  {
    "id": 7084,
    "origin": "sear",
    "examples": [
      {
        "exam_en": "He <strong class=\"target-word\">seared</strong> the steak over high heat.",
        "exam_ko": "그는 강한 불로 스테이크 표면을 <strong class=\"target-word\">태웠다</strong>."
      },
      {
        "exam_en": "She <strong class=\"target-word\">seared</strong> her finger on the hot iron.",
        "exam_ko": "그녀는 뜨거운 다리미에 손가락을 <strong class=\"target-word\">데었다</strong>."
      },
      {
        "exam_en": "I want you to <strong class=\"target-word\">sear</strong> the meat first to retain its juices.",
        "exam_ko": "먼저 고기를 <strong class=\"target-word\">재빨리 구워서</strong> 육즙이 빠져나가지 않도록 하세요."
      }
    ]
  },
  {
    "id": 7086,
    "origin": "pest",
    "examples": [
      {
        "exam_en": "Aphids are a common garden <strong class=\"target-word\">pest</strong> that damage plants.",
        "exam_ko": "진딧물은 식물을 해치는 흔한 정원 <strong class=\"target-word\">해충</strong>이다."
      },
      {
        "exam_en": "The farmer called a specialist for <strong class=\"target-word\">pest</strong> control.",
        "exam_ko": "농부는 <strong class=\"target-word\">해충</strong> 구제를 위해 전문가를 불렀다."
      }
    ]
  },
  {
    "id": 7089,
    "origin": "watershed",
    "examples": [
      {
        "exam_en": "The invention of the internet was a <strong class=\"target-word\">watershed</strong> moment in history.",
        "exam_ko": "인터넷의 발명은 역사적 <strong class=\"target-word\">전환점</strong>이었다."
      }
    ]
  },
  {
    "id": 7090,
    "origin": "residual",
    "examples": [
      {
        "exam_en": "She still felt <strong class=\"target-word\">residual</strong> pain weeks after the surgery.",
        "exam_ko": "그녀는 수술 후 몇 주가 지나도 <strong class=\"target-word\">잔존하는</strong> 통증을 느꼈다."
      },
      {
        "exam_en": "The actor receives <strong class=\"target-word\">residual</strong> income from reruns of the show.",
        "exam_ko": "그 배우는 프로그램 재방송으로 <strong class=\"target-word\">잔여</strong> 수입을 받는다."
      }
    ]
  },
  {
    "id": 7092,
    "origin": "align",
    "examples": [
      {
        "exam_en": "He carefully <strong class=\"target-word\">aligned</strong> the sights of the rifle before firing.",
        "exam_ko": "그는 발사 전에 소총의 조준을 신중하게 <strong class=\"target-word\">맞추었다</strong>."
      },
      {
        "exam_en": "The two countries <strong class=\"target-word\">aligned</strong> their policies on trade.",
        "exam_ko": "두 나라는 무역 정책을 <strong class=\"target-word\">일치시켰다</strong>."
      },
      {
        "exam_en": "<strong class=\"target-word\">Align</strong> all outlets horizontally for a neat appearance.",
        "exam_ko": "깔끔한 외관을 위해 모든 콘센트를 가로로 <strong class=\"target-word\">정렬하세요</strong>."
      }
    ]
  },
  {
    "id": 7093,
    "origin": "pernicious",
    "examples": [
      {
        "exam_en": "That ideology is <strong class=\"target-word\">pernicious</strong> to society.",
        "exam_ko": "그 이데올로기는 사회에 <strong class=\"target-word\">해롭다</strong>."
      },
      {
        "exam_en": "The doctor warned about a <strong class=\"target-word\">pernicious</strong> disease spreading in the region.",
        "exam_ko": "의사는 그 지역에 <strong class=\"target-word\">치명적인</strong> 질병이 퍼지고 있다고 경고했다."
      },
      {
        "exam_en": "The <strong class=\"target-word\">pernicious</strong> effects of pollution on the environment are evident.",
        "exam_ko": "오염의 <strong class=\"target-word\">해로운</strong> 영향은 환경에 분명하게 나타난다."
      }
    ]
  },
  {
    "id": 7095,
    "origin": "spurious",
    "examples": [
      {
        "exam_en": "His display of emotion on that occasion had been <strong class=\"target-word\">spurious</strong>.",
        "exam_ko": "그런 상황에서의 그의 감정 표현은 <strong class=\"target-word\">가짜</strong>였다."
      },
      {
        "exam_en": "The document was challenged due to <strong class=\"target-word\">spurious</strong> claims.",
        "exam_ko": "문서는 <strong class=\"target-word\">허위</strong> 주장으로 인해 의심받았다."
      }
    ]
  },
  {
    "id": 7099,
    "origin": "reminder",
    "examples": [
      {
        "exam_en": "The bell served as a <strong class=\"target-word\">reminder</strong> that I had an appointment.",
        "exam_ko": "벨 소리는 약속이 있다는 것을 알려주는 <strong class=\"target-word\">알림</strong> 역할을 했다."
      },
      {
        "exam_en": "The library sent me a <strong class=\"target-word\">reminder</strong> about the overdue books.",
        "exam_ko": "도서관에서 기일이 지난 책에 대한 <strong class=\"target-word\">독촉장</strong>이 왔다."
      }
    ]
  },
  {
    "id": 7100,
    "origin": "undercut",
    "examples": [
      {
        "exam_en": "The company gained an edge by <strong class=\"target-word\">undercutting</strong> prices in the market.",
        "exam_ko": "회사는 시장에서 가격을 <strong class=\"target-word\">낮춰</strong> 경쟁 우위를 차지했다."
      }
    ]
  },
  {
    "id": 7101,
    "origin": "preach",
    "examples": [
      {
        "exam_en": "The missionary traveled abroad to <strong class=\"target-word\">preach</strong> the gospel.",
        "exam_ko": "선교사는 복음을 <strong class=\"target-word\">전도하기</strong> 위해 해외로 떠났다."
      },
      {
        "exam_en": "The priest <strong class=\"target-word\">preached</strong> that we are sons of God.",
        "exam_ko": "목사는 우리는 하나님의 아들이라고 <strong class=\"target-word\">설교했다</strong>."
      }
    ]
  },
  {
    "id": 7104,
    "origin": "umbrage",
    "examples": [
      {
        "exam_en": "His rude comment gave <strong class=\"target-word\">umbrage</strong> to everyone present.",
        "exam_ko": "그의 무례한 발언은 참석한 모든 사람에게 <strong class=\"target-word\">불쾌감</strong>을 주었다."
      },
      {
        "exam_en": "She took <strong class=\"target-word\">umbrage</strong> at the criticism and left the room.",
        "exam_ko": "그녀는 비판에 <strong class=\"target-word\">화를 내며</strong> 방을 나갔다."
      },
      {
        "exam_en": "He took <strong class=\"target-word\">umbrage</strong> at the comment, feeling offended by the insinuation.",
        "exam_ko": "그는 빗댄 발언에 <strong class=\"target-word\">불쾌감</strong>을 표했다."
      }
    ]
  }
]
